vectorstackai/__init__.py
vectorstackai/__version__.py
vectorstackai/client.py
vectorstackai/error.py
vectorstackai/utils.py
vectorstackai/api_resources/__init__.py
vectorstackai/api_resources/base.py
vectorstackai/api_resources/embeddings.py
vectorstackai/api_resources/index.py
vectorstackai/objects/__init__.py
vectorstackai/objects/embeddings.py
vectorstackai/objects/index.py
vectorstackai-0.2.4.dist-info/LICENSE
vectorstackai-0.2.4.dist-info/METADATA
vectorstackai-0.2.4.dist-info/WHEEL
vectorstackai-0.2.4.dist-info/top_level.txt
vectorstackai-0.2.4.dist-info/RECORD
