Metadata-Version: 2.1
Name: vectorstackai
Version: 0.2.4
Summary: VectorStack AI's Official Python Library
Author: Shreyas Saxena
Author-email: shreyas@vectorstack.ai
License: MIT
Requires-Python: >=3.8
License-File: LICENSE
Requires-Dist: requests>=2.32.3
Requires-Dist: tenacity==8.5.0
Requires-Dist: numpy>=1.26.0
